webtool/__init__.py
webtool/auth/__init__.py
webtool/auth/backend.py
webtool/auth/dependencies.py
webtool/auth/manager.py
webtool/auth/models.py
webtool/auth/rotator.py
webtool/auth/service.py
webtool/cache/__init__.py
webtool/cache/client.py
webtool/cache/lock.py
webtool/db/__init__.py
webtool/db/client.py
webtool/logger/__init__.py
webtool/logger/dev_handler.py
webtool/logger/dev_logger.py
webtool/throttle/__init__.py
webtool/throttle/decorator.py
webtool/throttle/limiter.py
webtool/throttle/middleware.py
webtool/utils/__init__.py
webtool/utils/hash.py
webtool/utils/json.py
webtool/utils/key.py
webtool/utils/request.py
webtool/utils/response.py
webtool-0.1.14.dist-info/LICENSE
webtool-0.1.14.dist-info/METADATA
webtool-0.1.14.dist-info/WHEEL
webtool-0.1.14.dist-info/RECORD
