Metadata-Version: 2.3
Name: webtool
Version: 0.1.14
Summary: FastAPI/Starlette library for authentication, throttling, caching.
License: Apache-2.0
Keywords: fastapi,starlette,throttle,cache,utils
Author: IIH
Author-email: ds5105119@gmail.com
Maintainer: IIH
Maintainer-email: ds5105119@gmail.com
Requires-Python: >=3.11,<4.0
Classifier: License :: OSI Approved :: Apache Software License
Classifier: Programming Language :: Python :: 3
Classifier: Programming Language :: Python :: 3.11
Classifier: Programming Language :: Python :: 3.12
Classifier: Programming Language :: Python :: 3.13
Requires-Dist: argon2-cffi (>=23.1.0,<24.0.0)
Requires-Dist: orjson (>=3.10.11,<4.0.0)
Requires-Dist: pyjwt[crypto] (>=2.10.0,<3.0.0)
Requires-Dist: python-keycloak (>=5.1.1,<6.0.0)
Requires-Dist: redis[hiredis] (>=6.0.0,<7.0.0)
Requires-Dist: sqlalchemy (>=2.0.36,<3.0.0)
Project-URL: Repository, https://github.com/ds5105119/webtool
